{
  "notifications": [
    {
      "id": 1,
      "type": 1,
      "receiver_id": 2,
      "sender_id": 1,
      "created_at": "Fri Nov 10 2023 21:18:05 GMT+0300 (GMT+03:00)",
      "updated_at": "Fri Nov 10 2023 21:18:18 GMT+0300 (GMT+03:00)",
      "seen": false,
      "read": false,
      "is_removed": true
    },
    {
      "id": 2,
      "type": 5,
      "receiver_id": 1,
      "sender_id": 2,
      "created_at": "Fri Nov 10 2023 21:18:18 GMT+0300 (GMT+03:00)",
      "updated_at": "Fri Nov 10 2023 21:18:18 GMT+0300 (GMT+03:00)",
      "seen": true,
      "read": false,
      "is_removed": false
    },
    {
      "id": 3,
      "type": 4,
      "receiver_id": 2,
      "sender_id": 1,
      "created_at": "Fri Nov 10 2023 21:18:18 GMT+0300 (GMT+03:00)",
      "updated_at": "Fri Nov 10 2023 21:18:18 GMT+0300 (GMT+03:00)",
      "seen": true,
      "read": false,
      "is_removed": false
    },
    {
      "id": 4,
      "type": 1,
      "receiver_id": 1,
      "sender_id": 2,
      "created_at": "Fri Nov 10 2023 21:21:16 GMT+0300 (GMT+03:00)",
      "updated_at": "Fri Nov 10 2023 21:21:27 GMT+0300 (GMT+03:00)",
      "seen": false,
      "read": false,
      "is_removed": true
    },
    {
      "id": 5,
      "type": 5,
      "receiver_id": 2,
      "sender_id": 1,
      "created_at": "Fri Nov 10 2023 21:21:27 GMT+0300 (GMT+03:00)",
      "updated_at": "Fri Nov 10 2023 21:21:27 GMT+0300 (GMT+03:00)",
      "seen": true,
      "read": false,
      "is_removed": false
    },
    {
      "id": 6,
      "type": 4,
      "receiver_id": 1,
      "sender_id": 2,
      "created_at": "Fri Nov 10 2023 21:21:27 GMT+0300 (GMT+03:00)",
      "updated_at": "Fri Nov 10 2023 21:21:27 GMT+0300 (GMT+03:00)",
      "seen": true,
      "read": false,
      "is_removed": false
    },
    {
      "id": 7,
      "type": 1,
      "receiver_id": 2,
      "sender_id": 1,
      "created_at": "Fri Nov 10 2023 21:21:34 GMT+0300 (GMT+03:00)",
      "updated_at": "Fri Nov 10 2023 21:21:37 GMT+0300 (GMT+03:00)",
      "seen": false,
      "read": false,
      "is_removed": true
    },
    {
      "id": 8,
      "type": 2,
      "receiver_id": 2,
      "sender_id": 1,
      "created_at": "Fri Nov 10 2023 21:37:16 GMT+0300 (GMT+03:00)",
      "updated_at": "Fri Nov 10 2023 21:37:16 GMT+0300 (GMT+03:00)",
      "seen": true,
      "read": false,
      "is_removed": false
    },
    {
      "id": 9,
      "type": 1,
      "receiver_id": 2,
      "sender_id": 1,
      "created_at": "Fri Nov 10 2023 21:42:08 GMT+0300 (GMT+03:00)",
      "updated_at": "Sat Nov 25 2023 12:43:47 GMT+0300 (GMT+03:00)",
      "seen": false,
      "read": false,
      "is_removed": true
    },
    {
      "id": 10,
      "type": 2,
      "receiver_id": 2,
      "sender_id": 1,
      "created_at": "Sat Nov 25 2023 11:51:17 GMT+0300 (GMT+03:00)",
      "updated_at": "Sat Nov 25 2023 11:51:17 GMT+0300 (GMT+03:00)",
      "seen": true,
      "read": false,
      "is_removed": false
    },
    {
      "id": 11,
      "type": 2,
      "receiver_id": 2,
      "sender_id": 1,
      "created_at": "Sat Nov 25 2023 12:28:31 GMT+0300 (GMT+03:00)",
      "updated_at": "Sat Nov 25 2023 12:28:31 GMT+0300 (GMT+03:00)",
      "seen": true,
      "read": false,
      "is_removed": false
    },
    {
      "id": 12,
      "type": 2,
      "receiver_id": 2,
      "sender_id": 1,
      "created_at": "Sat Nov 25 2023 12:42:17 GMT+0300 (GMT+03:00)",
      "updated_at": "Sat Nov 25 2023 12:42:17 GMT+0300 (GMT+03:00)",
      "seen": true,
      "read": true,
      "is_removed": false
    },
    {
      "id": 13,
      "type": 1,
      "receiver_id": 2,
      "sender_id": 1,
      "created_at": "Sat Nov 25 2023 12:43:50 GMT+0300 (GMT+03:00)",
      "updated_at": "Sun Nov 26 2023 16:56:41 GMT+0300 (GMT+03:00)",
      "seen": false,
      "read": false,
      "is_removed": true
    },
    {
      "id": 14,
      "type": 1,
      "receiver_id": 2,
      "sender_id": 1,
      "created_at": "Sun Nov 26 2023 16:56:42 GMT+0300 (GMT+03:00)",
      "updated_at": "Sun Nov 26 2023 16:56:43 GMT+0300 (GMT+03:00)",
      "seen": false,
      "read": false,
      "is_removed": true
    },
    {
      "id": 15,
      "type": 1,
      "receiver_id": 2,
      "sender_id": 1,
      "created_at": "Sun Nov 26 2023 16:56:43 GMT+0300 (GMT+03:00)",
      "updated_at": "Sun Nov 26 2023 16:56:44 GMT+0300 (GMT+03:00)",
      "seen": false,
      "read": false,
      "is_removed": true
    },
    {
      "id": 16,
      "type": 2,
      "receiver_id": 2,
      "sender_id": 1,
      "created_at": "Mon Nov 27 2023 16:40:00 GMT+0300 (GMT+03:00)",
      "updated_at": "Mon Nov 27 2023 16:40:00 GMT+0300 (GMT+03:00)",
      "seen": true,
      "read": true,
      "is_removed": false
    },
    {
      "id": 17,
      "type": 1,
      "receiver_id": 2,
      "sender_id": 1,
      "created_at": "Mon Nov 27 2023 16:40:01 GMT+0300 (GMT+03:00)",
      "updated_at": "Mon Nov 27 2023 19:10:37 GMT+0300 (GMT+03:00)",
      "seen": true,
      "read": false,
      "is_removed": true
    },
    {
      "id": 18,
      "type": 3,
      "receiver_id": 2,
      "sender_id": 1,
      "created_at": "Mon Nov 27 2023 19:09:44 GMT+0300 (GMT+03:00)",
      "updated_at": "Mon Nov 27 2023 19:09:44 GMT+0300 (GMT+03:00)",
      "seen": true,
      "read": true,
      "is_removed": false
    },
    {
      "id": 19,
      "type": 5,
      "receiver_id": 1,
      "sender_id": 2,
      "created_at": "Mon Nov 27 2023 19:10:37 GMT+0300 (GMT+03:00)",
      "updated_at": "Mon Nov 27 2023 19:10:37 GMT+0300 (GMT+03:00)",
      "seen": false,
      "read": false,
      "is_removed": false
    },
    {
      "id": 20,
      "type": 4,
      "receiver_id": 2,
      "sender_id": 1,
      "created_at": "Mon Nov 27 2023 19:10:37 GMT+0300 (GMT+03:00)",
      "updated_at": "Mon Nov 27 2023 19:10:37 GMT+0300 (GMT+03:00)",
      "seen": true,
      "read": true,
      "is_removed": false
    }
  ]
}